README.rst
setup.py
django_localflavor_nz/__init__.py
django_localflavor_nz/forms.py
django_localflavor_nz/models.py
django_localflavor_nz/nz_councils.py
django_localflavor_nz/nz_provinces.py
django_localflavor_nz/nz_regions.py
django_localflavor_nz/tests.py
django_localflavor_nz.egg-info/PKG-INFO
django_localflavor_nz.egg-info/SOURCES.txt
django_localflavor_nz.egg-info/dependency_links.txt
django_localflavor_nz.egg-info/requires.txt
django_localflavor_nz.egg-info/top_level.txt