Metadata-Version: 1.1
Name: django-localflavor-nz
Version: 1.1
Summary: Country-specific Django helpers for New Zealand.
Home-page: https://bitbucket.org/markuz/django-localflavor-nz
Author: Marek Kuziel
Author-email: marek@kuziel.info
License: BSD
Platform: UNKNOWN
Classifier: Development Status :: 5 - Production/Stable
Classifier: Environment :: Web Environment
Classifier: Framework :: Django
Classifier: Intended Audience :: Developers
Classifier: License :: OSI Approved :: BSD License
Classifier: Operating System :: OS Independent
Classifier: Programming Language :: Python
